ambition_subject/__init__.py
ambition_subject/action_items.py
ambition_subject/admin_site.py
ambition_subject/apps.py
ambition_subject/choices.py
ambition_subject/consents.py
ambition_subject/constants.py
ambition_subject/data_manager.py
ambition_subject/identifiers.py
ambition_subject/managers.py
ambition_subject/mommy_recipes.py
ambition_subject/notifications.py
ambition_subject/offline_models.py
ambition_subject/patterns.py
ambition_subject/urls.py
ambition_subject/validators.py
ambition_subject/wsgi.py
ambition_subject/admin/__init__.py
ambition_subject/admin/education_admin.py
ambition_subject/admin/education_hoh_admin.py
ambition_subject/admin/follow_up_admin.py
ambition_subject/admin/lumbar_puncture_csf_admin.py
ambition_subject/admin/medical_expenses_admin.py
ambition_subject/admin/medical_expenses_two_admin.py
ambition_subject/admin/microbiology_admin.py
ambition_subject/admin/modeladmin.py
ambition_subject/admin/patient_history_admin.py
ambition_subject/admin/pk_pd_crf_admin.py
ambition_subject/admin/radiology_admin.py
ambition_subject/admin/subject_consent_admin.py
ambition_subject/admin/subject_reconsent_admin.py
ambition_subject/admin/subject_requisition_admin.py
ambition_subject/admin/subject_visit_admin.py
ambition_subject/admin/week16_admin.py
ambition_subject/admin/week2_admin.py
ambition_subject/admin/week4_admin.py
ambition_subject/admin/blood_result_admin/__init__.py
ambition_subject/admin/blood_result_admin/blood_result_admin.py
ambition_subject/admin/blood_result_admin/fieldsets.py
ambition_subject/forms/__init__.py
ambition_subject/forms/amphotericin_missed_doses_form.py
ambition_subject/forms/blood_result_form.py
ambition_subject/forms/education_form.py
ambition_subject/forms/education_hoh_form.py
ambition_subject/forms/fluconazole_missed_doses_form.py
ambition_subject/forms/flucytosine_missed_doses_form.py
ambition_subject/forms/follow_up_form.py
ambition_subject/forms/form_mixins.py
ambition_subject/forms/lumbar_puncture_csf_form.py
ambition_subject-0.1.94.dist-info/AUTHORS
ambition_subject-0.1.94.dist-info/LICENSE
ambition_subject-0.1.94.dist-info/METADATA
ambition_subject-0.1.94.dist-info/WHEEL
ambition_subject-0.1.94.dist-info/top_level.txt
ambition_subject-0.1.94.dist-info/RECORD
