Metadata-Version: 2.1
Name: ambition-subject
Version: 0.1.94
Summary: Subject/Participant models for ambition/edc.
Home-page: https://github.com/ambition-trial/ambition-subject
Author: Erik van Widenfelt
Author-email: ew2789@gmail.com
License: GPL license, see LICENSE
Keywords: django ambition
Platform: UNKNOWN
Classifier: Environment :: Web Environment
Classifier: Framework :: Django
Classifier: Intended Audience :: Developers
Classifier: Intended Audience :: Science/Research
Classifier: License :: OSI Approved :: GNU General Public License v3 (GPLv3)
Classifier: Operating System :: OS Independent
Classifier: Programming Language :: Python :: 3.7
Classifier: Topic :: Internet :: WWW/HTTP
Classifier: Topic :: Internet :: WWW/HTTP :: Dynamic Content
Requires-Python: >=3.7
Requires-Dist: ambition-auth
Requires-Dist: ambition-rando
Requires-Dist: ambition-prn
Requires-Dist: ambition-ae
Requires-Dist: ambition-labs
Requires-Dist: ambition-lists
Requires-Dist: ambition-metadata-rules
Requires-Dist: ambition-reference
Requires-Dist: ambition-sites
Requires-Dist: ambition-screening
Requires-Dist: ambition-form-validators
Requires-Dist: ambition-visit-schedule
Requires-Dist: django-collect-offline
Requires-Dist: django-collect-offline-files
Requires-Dist: edc-action-item
Requires-Dist: edc-adverse-event
Requires-Dist: edc-data-manager
Requires-Dist: edc-appointment
Requires-Dist: edc-consent
Requires-Dist: edc-form-describer
Requires-Dist: edc-form-label
Requires-Dist: edc-model-admin
Requires-Dist: edc-notification
Requires-Dist: edc-offstudy
Requires-Dist: edc-reportable
Requires-Dist: edc-subject-dashboard
